Workbook

Sheet Comps_Analysis
A1: Company | B1: Year | C1: Price | D1: Shares Outstanding | E1: Total Debt | F1: Cash | G1: EBITDA | H1: Market Cap | I1: Enterprise Value | J1: EV/EBITDA
A2: CNQ | B2: 2022 | C2: 31.554224 | D2: 2205272000 | E2: 11445000000 | F2: 920000000 | G2: 21727000000 | H2: =C2*D2 -> 6.9585647e+10 | I2: =H2+E2-F2 -> 8.0110647e+10 | J2: =I2/G2 -> 3.6871472
A3: CNQ | B3: 2023 | C3: 38.200382 | D3: 2144816000 | E3: 10799000000 | F3: 877000000 | G3: 17269000000 | H3: =C3*D3 -> 8.1932791e+10 | I3: =H3+E3-F3 -> 9.1854791e+10 | J3: =I3/G3 -> 5.3190568
A4: CNQ | B4: 2024 | C4: 40.914742 | D4: 2102996000 | E4: 18819000000 | F4: 131000000 | G4: 15413000000 | H4: =C4*D4 -> 8.6043538e+10 | I4: =H4+E4-F4 -> 1.0473154e+11 | J4: =I4/G4 -> 6.7950132
A5: CNQ | B5: 2025 | C5: 45.17947 | D5: 2081578000 | E5: 16617000000 | F5: 673000000 | G5: 21887000000 | H5: =C5*D5 -> 9.4044591e+10 | I5: =H5+E5-F5 -> 1.0998859e+11 | J5: =I5/G5 -> 5.0252931
A6: CVE | B6: 2022 | C6: 23.656223 | D6: 1909190000 | E6: 11642000000 | F6: 4524000000 | G6: 14222000000 | H6: =C6*D6 -> 4.5164225e+10 | I6: =H6+E6-F6 -> 5.2282225e+10 | J6: =I6/G6 -> 3.6761514
A7: CVE | B7: 2023 | C7: 20.327997 | D7: 1871868729 | E7: 9945000000 | F7: 2227000000 | G7: 10407000000 | H7: =C7*D7 -> 3.8051342e+10 | I7: =H7+E7-F7 -> 4.5769342e+10 | J7: =I7/G7 -> 4.3979381
A8: CVE | B8: 2024 | C8: 20.761627 | D8: 1823038000 | E8: 10634000000 | F8: 3093000000 | G8: 9591000000 | H8: =C8*D8 -> 3.7849235e+10 | I8: =H8+E8-F8 -> 4.5390235e+10 | J8: =I8/G8 -> 4.7325863
A9: CVE | B9: 2025 | C9: 22.947155 | D9: 1883400091 | E9: 14207000000 | F9: 2740000000 | G9: 10330000000 | H9: =C9*D9 -> 4.3218674e+10 | I9: =H9+E9-F9 -> 5.4685674e+10 | J9: =I9/G9 -> 5.2938697
A10: SU | B10: 2022 | C10: 36.822819 | D10: 1337470739 | E10: 15619000000 | F10: 1980000000 | G10: 22008000000 | H10: =C10*D10 -> 4.9249443e+10 | I10: =H10+E10-F10 -> 6.2888443e+10 | J10: =I10/G10 -> 2.8575265
A11: SU | B11: 2023 | C11: 38.19487 | D11: 1290099792 | E11: 15407000000 | F11: 1729000000 | G11: 17810000000 | H11: =C11*D11 -> 4.9275194e+10 | I11: =H11+E11-F11 -> 6.2953194e+10 | J11: =I11/G11 -> 3.5347105
A12: SU | B12: 2024 | C12: 48.179405 | D12: 1244331601 | E12: 14689000000 | F12: 3484000000 | G12: 15835000000 | H12: =C12*D12 -> 5.9951156e+10 | I12: =H12+E12-F12 -> 7.1156156e+10 | J12: =I12/G12 -> 4.4936
A13: SU | B13: 2025 | C13: 59.671684 | D13: 1193519494 | E13: 14504000000 | F13: 3650000000 | G13: 15607000000 | H13: =C13*D13 -> 7.1219318e+10 | I13: =H13+E13-F13 -> 8.2073318e+10 | J13: =I13/G13 -> 5.2587505
... A17: IMO | B17: 2025 | C17: 116.80293 | D17: 483592715 | E17: 4146000000 | F17: 1142000000 | G17: 6867000000 | H17: =C17*D17 -> 5.6485047e+10 | I17: =H17+E17-F17 -> 5.9489047e+10 | J17: =I17/G17 -> 8.663033
A20: Peer Average EV/EBITDA (2022-2025)
A21: CNQ | B21: =AVERAGE(J2:J5) -> 5.2066276
A22: CVE | B22: =AVERAGE(J6:J9) -> 4.5251364
A23: SU | B23: =AVERAGE(J10:J13) -> 4.0361469
A24: IMO | B24: =AVERAGE(J14:J17) -> 5.5845446
A25: Peer Average (CVE, SU, IMO only) | B25: =AVERAGE(B22:B24) -> 4.7152759
A26: CNQ Average EBITDA (2022-2025) | B26: =AVERAGE(G2:G5) -> 19074000000
A27: CNQ Average Total Debt (2022-2025) | B27: =AVERAGE(E2:E5) -> 14420000000
A28: CNQ Average Cash (2022-2025) | B28: =AVERAGE(F2:F5) -> 650250000
A29: CNQ Average Shares Outstanding | B29: =AVERAGE(D2:D5) -> 2133665500
A30: Implied Enterprise Value | B30: =B25*B26 -> 8.9939173e+10
A31: Implied Market Cap | B31: =B30-B27+B28 -> 7.6169423e+10
A32: Implied Share Price | B32: =B31/B29 -> 35.698859
A33: Premium to peer-implied fair value | B33: =((45.18-35.7)/35.7)*100 -> 26.554622

Sheet Price_vs_Fundamentals
A1: Company | B1: Year | C1: Revenue | D1: EBITDA | E1: Price | F1: Revenue Growth % | G1: EBITDA Growth % | H1: Price Growth %
A2: CNQ | B2: 2022 | C2: 49530000000 | D2: 21727000000 | E2: 31.554224
A3: CNQ | B3: 2023 | C3: 40835000000 | D3: 17269000000 | E3: 38.200382 | F3: =(C3-C2)/C2 -> -0.17555017 | G3: =(D3-D2)/D2 -> -0.20518249 | H3: =(E3-E2)/E2 -> 0.21062658
A4: CNQ | B4: 2024 | C4: 41509000000 | D4: 15413000000 | E4: 40.914742 | F4: =(C4-C3)/C3 -> 0.016505449 | G4: =(D4-D3)/D3 -> -0.10747582 | H4: =(E4-E3)/E3 -> 0.071055815
A5: CNQ | B5: 2025 | C5: 44167000000 | D5: 21887000000 | E5: 45.17947 | F5: =(C5-C4)/C4 -> 0.064034306 | G5: =(D5-D4)/D4 -> 0.42003504 | H5: =(E5-E4)/E4 -> 0.10423452
A6: CVE | B6: 2022 | C6: 71765000000 | D6: 14222000000 | E6: 23.656223
A7: CVE | B7: 2023 | C7: 55474000000 | D7: 10407000000 | E7: 20.327997 | F7: =(C7-C6)/C6 -> -0.22700481 | G7: =(D7-D6)/D6 -> -0.26824638 | H7: =(E7-E6)/E6 -> -0.14069135
A8: CVE | B8: 2024 | C8: 57726000000 | D8: 9591000000 | E8: 20.761627 | F8: =(C8-C7)/C7 -> 0.040595594 | G8: =(D8-D7)/D7 -> -0.078408763 | H8: =(E8-E7)/E7 -> 0.021331663
A9: CVE | B9: 2025 | C9: 52751000000 | D9: 10330000000 | E9: 22.947155 | F9: =(C9-C8)/C8 -> -0.086183002 | G9: =(D9-D8)/D8 -> 0.077051402 | H9: =(E9-E8)/E8 -> 0.10526765
A10: SU | B10: 2022 | C10: 62907000000 | D10: 22008000000 | E10: 36.822819
A11: SU | B11: 2023 | C11: 52206000000 | D11: 17810000000 | E11: 38.19487 | F11: =(C11-C10)/C10 -> -0.17010826 | G11: =(D11-D10)/D10 -> -0.19074882 | H11: =(E11-E10)/E10 -> 0.037260897
A12: SU | B12: 2024 | C12: 54881000000 | D12: 15835000000 | E12: 48.179405 | F12: =(C12-C11)/C11 -> 0.051239321 | G12: =(D12-D11)/D11 -> -0.11089276 | H12: =(E12-E11)/E11 -> 0.26141037
A13: SU | B13: 2025 | C13: 52377000000 | D13: 15607000000 | E13: 59.671684 | F13: =(C13-C12)/C12 -> -0.045625991 | G13: =(D13-D12)/D12 -> -0.014398484 | H13: =(E13-E12)/E12 -> 0.23853094
A14: IMO | B14: 2022 | C14: 57234000000 | D14: 11441000000 | E14: 60.035564
A15: IMO | B15: 2023 | C15: 48300000000 | D15: 8345000000 | E15: 70.624214 | F15: =(C15-C14)/C14 -> -0.15609603 | G15: =(D15-D14)/D14 -> -0.27060572 | H15: =(E15-E14)/E14 -> 0.17637295
A16: IMO | B16: 2024 | C16: 48824000000 | D16: 8263000000 | E16: 85.010132 | F16: =(C16-C15)/C15 -> 0.010848861 | G16: =(D16-D15)/D15 -> -0.0098262433 | H16: =(E16-E15)/E15 -> 0.20369668
A17: IMO | B17: 2025 | C17: 45203000000 | D17: 6867000000 | E17: 116.80293 | F17: =(C17-C16)/C16 -> -0.074164345 | G17: =(D17-D16)/D16 -> -0.1689459 | H17: =(E17-E16)/E16 -> 0.37398837
A20: Company | B20: Year | C20: Indexed EBITDA | D20: Indexed Price
A21: CNQ | B21: 2022 | C21: 100 | D21: 100
A22: CNQ | B22: 2023 | C22: =(D3/D2)*100 -> 79.481751 | D22: =(E3/E2)*100 -> 121.06266
A23: CNQ | B23: 2024 | C23: =(D4/D2)*100 -> 70.939384 | D23: =(E4/E2)*100 -> 129.66486
A24: CNQ | B24: 2025 | C24: =(D5/D2)*100 -> 100.73641 | D24: =(E5/E2)*100 -> 143.18042
A25: CVE | B25: 2022 | C25: 100 | D25: 100
A26: CVE | B26: 2023 | C26: =(D7/D6)*100 -> 73.175362 | D26: =(E7/E6)*100 -> 85.930865
A27: CVE | B27: 2024 | C27: =(D8/D6)*100 -> 67.437772 | D27: =(E8/E6)*100 -> 87.763913
A28: CVE | B28: 2025 | C28: =(D9/D6)*100 -> 72.633947 | D28: =(E9/E6)*100 -> 97.002614
A29: SU | B29: 2022 | C29: 100 | D29: 100
A30: SU | B30: 2023 | C30: =(D11/D10)*100 -> 80.925118 | D30: =(E11/E10)*100 -> 103.72609
A31: SU | B31: 2024 | C31: =(D12/D10)*100 -> 71.951109 | D31: =(E12/E11)*100 -> 126.14104
A32: SU | B32: 2025 | C32: =(D13/D10)*100 -> 70.915122 | D32: =(E13/E12)*100 -> 123.85309
A33: IMO | B33: 2022 | C33: 100 | D33: 100
A34: IMO | B34: 2023 | C34: =(D15/D14)*100 -> 72.939428 | D34: =(E15/E14)*100 -> 117.6373
A35: IMO | B35: 2024 | C35: =(D16/D14)*100 -> 72.222708 | D35: =(E16/E15)*100 -> 120.36967
A36: IMO | B36: 2025 | C36: =(D17/D14)*100 -> 60.020977 | D36: =(E17/E16)*100 -> 137.39884

Sheet Oil_Macro_Analysis
A1: Year | B1: Avg Oil Price
A2: 2022 | B2: =AVERAGEIFS(Oil_Price!B:B, Oil_Price!A:A, ">="&DATE(2022,1,1), Oil_Price!A:A, "<="&DATE(2022,12,31)) -> 94.331474
A3: 2023 | B3: =AVERAGEIFS(Oil_Price!B:B, Oil_Price!A:A, ">="&DATE(2023,1,1), Oil_Price!A:A, "<="&DATE(2023,12,31)) -> 77.59712
A4: 2024 | B4: =AVERAGEIFS(Oil_Price!B:B, Oil_Price!A:A, ">="&DATE(2024,1,1), Oil_Price!A:A, "<="&DATE(2024,12,31)) -> 75.758016
A5: 2025 | B5: =AVERAGEIFS(Oil_Price!B:B, Oil_Price!A:A, ">="&DATE(2025,1,1), Oil_Price!A:A, "<="&DATE(2025,12,31)) -> 64.739524
A7: Forcast of 2026 | B7: Actual of 2026
A8: =_xlfn.FORECAST.LINEAR(2026, B2:B5, A2:A5) -> 55.452795 | B8: =AVERAGEIFS(Oil_Price!B:B, Oil_Price!A:A, ">="&DATE(2026,1,1), Oil_Price!A:A, "<="&DATE(2026,9,22)) -> 83.473536
A10: Daily Stock Price Sensitivity & Oil Beta (2022–2026)
A11: Company | B11: Stock Move per $1 Oil ($) | C11: Oil Beta (% Move / 1% Oil) | D11: R-Squared (R²)
A12: CNQ | B12: =SLOPE(Prices_All!G3:G1181, Prices_All!H3:H1181) -> 0.20960721 | C12: =SLOPE(Prices_All!E3:E1181, Prices_All!F3:F1181) -> 0.45887363 | D12: =RSQ(Prices_All!E3:E1181, Prices_All!F3:F1181) -> 0.39809168
A13: CVE | B13: =SLOPE(Prices_All!G1183:G2361, Prices_All!H1183:H2361) -> 0.14771822 | C13: =SLOPE(Prices_All!E1183:E2361, Prices_All!F1183:F2361) -> 0.5485978 | D13: =RSQ(Prices_All!E1183:E2361, Prices_All!F1183:F2361) -> 0.36866556
A14: SU | B14: =SLOPE(Prices_All!G2363:G3541, Prices_All!H2363:H3541) -> 0.24230664 | C14: =SLOPE(Prices_All!E2363:E3541, Prices_All!F2363:F3541) -> 0.43121564 | D14: =RSQ(Prices_All!E2363:E3541, Prices_All!F2363:F3541) -> 0.36455047
A15: IMO | B15: =SLOPE(Prices_All!G3543:G4721, Prices_All!H3543:H4721) -> 0.37769523 | C15: =SLOPE(Prices_All!E3543:E4721, Prices_All!F3543:F4721) -> 0.374238 | D15: =RSQ(Prices_All!E3543:E4721, Prices_All!F3543:F4721) -> 0.27430442

Sheet Fundamentals
A1: Company | B1: Year | C1: Metric | D1: Value
A2: CNQ | B2: 2022 | C2: Total Revenue | D2: 49530000000
A3: CVE | B3: 2022 | C3: Total Revenue | D3: 71765000000
A4: SU | B4: 2022 | C4: Total Revenue | D4: 62907000000
A5: IMO | B5: 2022 | C5: Total Revenue | D5: 57234000000
A6: CNQ | B6: 2022 | C6: EBITDA | D6: 21727000000
A7: CNQ | B7: 2023 | C7: EBITDA | D7: 17269000000
A8: CNQ | B8: 2024 | C8: EBITDA | D8: 15413000000
A9: CNQ | B9: 2025 | C9: EBITDA | D9: 21887000000
A10: CNQ | B10: 2025 | C10: EBIT | D10: 14280000000
A11: CNQ | B11: 2024 | C11: EBIT | D11: 8732000000
A12: CNQ | B12: 2023 | C12: EBIT | D12: 10856000000
A13: CNQ | B13: 2022 | C13: EBIT | D13: 14374000000
... A241: IMO | B241: 2025 | C241: Ordinary Shares Number | D241: 584153000

Sheet Prices_All
A1: Company | B1: Date | C1: Close
A2: CNQ | B2: 44565 | C2: 21.116488 | D2: =_xlfn.XLOOKUP(B2, Oil_Price!A:A, Oil_Price!B:B, "") -> 76.989998 | E2: =IFERROR(IF(AND(A2=A1, C2<>"", C1<>""), (C2-C1)/C1, ""), "") | F2: =IFERROR(IF(AND(A2=A1, D2<>"", D1<>""), (D2-D1)/D1, ""), "") | G2: =IFERROR(IF(AND(A2=A1, C2<>"", C1<>""), C2-C1, ""), "") | H2: =IFERROR(IF(AND(A2=A1, D2<>"", D1<>""), D2-D1, ""), "")
A3: CNQ | B3: 44566 | C3: 21.371286 | D3: =_xlfn.XLOOKUP(B3, Oil_Price!A:A, Oil_Price!B:B, "") -> 77.849998 | E3: =IFERROR(IF(AND(A3=A2, C3<>"", C2<>""), (C3-C2)/C2, ""), "") -> 0.012066348 | F3: =IFERROR(IF(AND(A3=A2, D3<>"", D2<>""), (D3-D2)/D2, ""), "") -> 0.01117029 | G3: =IFERROR(IF(AND(A3=A2, C3<>"", C2<>""), C3-C2, ""), "") -> 0.25479889 | H3: =IFERROR(IF(AND(A3=A2, D3<>"", D2<>""), D3-D2, ""), "") -> 0.86000061
A4: CNQ | B4: 44567 | C4: 22.467644 | D4: =_xlfn.XLOOKUP(B4, Oil_Price!A:A, Oil_Price!B:B, "") -> 79.459999 | E4: =IFERROR(IF(AND(A4=A3, C4<>"", C3<>""), (C4-C3)/C3, ""), "") -> 0.051300484 | F4: =IFERROR(IF(AND(A4=A3, D4<>"", D3<>""), (D4-D3)/D3, ""), "") -> 0.020680805 | G4: =IFERROR(IF(AND(A4=A3, C4<>"", C3<>""), C4-C3, ""), "") -> 1.0963573 | H4: =IFERROR(IF(AND(A4=A3, D4<>"", D3<>""), D4-D3, ""), "") -> 1.6100006
A5: CNQ | B5: 44568 | C5: 23.06987 | D5: =_xlfn.XLOOKUP(B5, Oil_Price!A:A, Oil_Price!B:B, "") -> 78.900002 | E5: =IFERROR(IF(AND(A5=A4, C5<>"", C4<>""), (C5-C4)/C4, ""), "") -> 0.026804157 | F5: =IFERROR(IF(AND(A5=A4, D5<>"", D4<>""), (D5-D4)/D4, ""), "") -> -0.0070475405 | G5: =IFERROR(IF(AND(A5=A4, C5<>"", C4<>""), C5-C4, ""), "") -> 0.60222626 | H5: =IFERROR(IF(AND(A5=A4, D5<>"", D4<>""), D5-D4, ""), "") -> -0.55999756
A6: CNQ | B6: 44571 | C6: 23.027397 | D6: =_xlfn.XLOOKUP(B6, Oil_Price!A:A, Oil_Price!B:B, "") -> 78.230003 | E6: =IFERROR(IF(AND(A6=A5, C6<>"", C5<>""), (C6-C5)/C5, ""), "") -> -0.0018410524 | F6: =IFERROR(IF(AND(A6=A5, D6<>"", D5<>""), (D6-D5)/D5, ""), "") -> -0.0084917384 | G6: =IFERROR(IF(AND(A6=A5, C6<>"", C5<>""), C6-C5, ""), "") -> -0.042472839 | H6: =IFERROR(IF(AND(A6=A5, D6<>"", D5<>""), D6-D5, ""), "") -> -0.66999817
A7: CNQ | B7: 44572 | C7: 23.436602 | D7: =_xlfn.XLOOKUP(B7, Oil_Price!A:A, Oil_Price!B:B, "") -> 81.220001 | E7: =IFERROR(IF(AND(A7=A6, C7<>"", C6<>""), (C7-C6)/C6, ""), "") -> 0.017770332 | F7: =IFERROR(IF(AND(A7=A6, D7<>"", D6<>""), (D7-D6)/D6, ""), "") -> 0.038220603 | G7: =IFERROR(IF(AND(A7=A6, C7<>"", C6<>""), C7-C6, ""), "") -> 0.40920448 | H7: =IFERROR(IF(AND(A7=A6, D7<>"", D6<>""), D7-D6, ""), "") -> 2.9899979
A8: CNQ | B8: 44573 | C8: 23.822645 | D8: =_xlfn.XLOOKUP(B8, Oil_Price!A:A, Oil_Price!B:B, "") -> 82.639999 | E8: =IFERROR(IF(AND(A8=A7, C8<>"", C7<>""), (C8-C7)/C7, ""), "") -> 0.016471823 | F8: =IFERROR(IF(AND(A8=A7, D8<>"", D7<>""), (D8-D7)/D7, ""), "") -> 0.017483356 | G8: =IFERROR(IF(AND(A8=A7, C8<>"", C7<>""), C8-C7, ""), "") -> 0.38604355 | H8: =IFERROR(IF(AND(A8=A7, D8<>"", D7<>""), D8-D7, ""), "") -> 1.4199982
A9: CNQ | B9: 44574 | C9: 24.285894 | D9: =_xlfn.XLOOKUP(B9, Oil_Price!A:A, Oil_Price!B:B, "") -> 82.120003 | E9: =IFERROR(IF(AND(A9=A8, C9<>"", C8<>""), (C9-C8)/C8, ""), "") -> 0.01944575 | F9: =IFERROR(IF(AND(A9=A8, D9<>"", D8<>""), (D9-D8)/D8, ""), "") -> -0.0062923118 | G9: =IFERROR(IF(AND(A9=A8, C9<>"", C8<>""), C9-C8, ""), "") -> 0.46324921 | H9: =IFERROR(IF(AND(A9=A8, D9<>"", D8<>""), D9-D8, ""), "") -> -0.51999664
A10: CNQ | B10: 44575 | C10: 25.162214 | D10: =_xlfn.XLOOKUP(B10, Oil_Price!A:A, Oil_Price!B:B, "") -> 83.82 | E10: =IFERROR(IF(AND(A10=A9, C10<>"", C9<>""), (C10-C9)/C9, ""), "") -> 0.036083492 | F10: =IFERROR(IF(AND(A10=A9, D10<>"", D9<>""), (D10-D9)/D9, ""), "") -> 0.020701375 | G10: =IFERROR(IF(AND(A10=A9, C10<>"", C9<>""), C10-C9, ""), "") -> 0.87631989 | H10: =IFERROR(IF(AND(A10=A9, D10<>"", D9<>""), D10-D9, ""), "") -> 1.6999969
A11: CNQ | B11: 44578 | C11: 25.532816 | D11: =_xlfn.XLOOKUP(B11, Oil_Price!A:A, Oil_Price!B:B, "") | E11: =IFERROR(IF(AND(A11=A10, C11<>"", C10<>""), (C11-C10)/C10, ""), "") -> 0.014728499 | F11: =IFERROR(IF(AND(A11=A10, D11<>"", D10<>""), (D11-D10)/D10, ""), "") | G11: =IFERROR(IF(AND(A11=A10, C11<>"", C10<>""), C11-C10, ""), "") -> 0.37060165 | H11: =IFERROR(IF(AND(A11=A10, D11<>"", D10<>""), D11-D10, ""), "")
A12: CNQ | B12: 44579 | C12: 25.509651 | D12: =_xlfn.XLOOKUP(B12, Oil_Price!A:A, Oil_Price!B:B, "") -> 85.43 | E12: =IFERROR(IF(AND(A12=A11, C12<>"", C11<>""), (C12-C11)/C11, ""), "") -> -0.00090725399 | F12: =IFERROR(IF(AND(A12=A11, D12<>"", D11<>""), (D12-D11)/D11, ""), "") | G12: =IFERROR(IF(AND(A12=A11, C12<>"", C11<>""), C12-C11, ""), "") -> -0.023164749 | H12: =IFERROR(IF(AND(A12=A11, D12<>"", D11<>""), D12-D11, ""), "")
A13: CNQ | B13: 44580 | C13: 25.579144 | D13: =_xlfn.XLOOKUP(B13, Oil_Price!A:A, Oil_Price!B:B, "") -> 86.959999 | E13: =IFERROR(IF(AND(A13=A12, C13<>"", C12<>""), (C13-C12)/C12, ""), "") -> 0.0027241588 | F13: =IFERROR(IF(AND(A13=A12, D13<>"", D12<>""), (D13-D12)/D12, ""), "") -> 0.017909385 | G13: =IFERROR(IF(AND(A13=A12, C13<>"", C12<>""), C13-C12, ""), "") -> 0.06949234 | H13: =IFERROR(IF(AND(A13=A12, D13<>"", D12<>""), D13-D12, ""), "") -> 1.5299988
... A4721: IMO | B4721: 46280 | C4721: 188.11 | D4721: =_xlfn.XLOOKUP(B4721, Oil_Price!A:A, Oil_Price!B:B, "") -> 105.83 | E4721: =IFERROR(IF(AND(A4721=A4720, C4721<>"", C4720<>""), (C4721-C4720)/C4720, ""), "") -> 0.026969496 | F4721: =IFERROR(IF(AND(A4721=A4720, D4721<>"", D4720<>""), (D4721-D4720)/D4720, ""), "") -> 0.043791325 | G4721: =IFERROR(IF(AND(A4721=A4720, C4721<>"", C4720<>""), C4721-C4720, ""), "") -> 4.9400024 | H4721: =IFERROR(IF(AND(A4721=A4720, D4721<>"", D4720<>""), D4721-D4720, ""), "") -> 4.4400024
D4722: =_xlfn.XLOOKUP(B4722, Oil_Price!A:A, Oil_Price!B:B, "") | E4722: =IFERROR(IF(AND(A4722=A4721, C4722<>"", C4721<>""), (C4722-C4721)/C4721, ""), "") | F4722: =IFERROR(IF(AND(A4722=A4721, D4722<>"", D4721<>""), (D4722-D4721)/D4721, ""), "") | G4722: =IFERROR(IF(AND(A4722=A4721, C4722<>"", C4721<>""), C4722-C4721, ""), "") | H4722: =IFERROR(IF(AND(A4722=A4721, D4722<>"", D4721<>""), D4722-D4721, ""), "")
D4723: =_xlfn.XLOOKUP(B4723, Oil_Price!A:A, Oil_Price!B:B, "") | E4723: =IFERROR(IF(AND(A4723=A4722, C4723<>"", C4722<>""), (C4723-C4722)/C4722, ""), "") | F4723: =IFERROR(IF(AND(A4723=A4722, D4723<>"", D4722<>""), (D4723-D4722)/D4722, ""), "") | G4723: =IFERROR(IF(AND(A4723=A4722, C4723<>"", C4722<>""), C4723-C4722, ""), "") | H4723: =IFERROR(IF(AND(A4723=A4722, D4723<>"", D4722<>""), D4723-D4722, ""), "")
D4724: =_xlfn.XLOOKUP(B4724, Oil_Price!A:A, Oil_Price!B:B, "") | E4724: =IFERROR(IF(AND(A4724=A4723, C4724<>"", C4723<>""), (C4724-C4723)/C4723, ""), "") | F4724: =IFERROR(IF(AND(A4724=A4723, D4724<>"", D4723<>""), (D4724-D4723)/D4723, ""), "") | G4724: =IFERROR(IF(AND(A4724=A4723, C4724<>"", C4723<>""), C4724-C4723, ""), "") | H4724: =IFERROR(IF(AND(A4724=A4723, D4724<>"", D4723<>""), D4724-D4723, ""), "")

Sheet Prices_2022-2025
A1: Company | B1: Date | C1: Close
A2: CNQ | B2: 44565 | C2: 21.116488
A3: CNQ | B3: 44566 | C3: 21.371286
A4: CNQ | B4: 44567 | C4: 22.467644
A5: CNQ | B5: 44568 | C5: 23.06987
A6: CNQ | B6: 44571 | C6: 23.027397
A7: CNQ | B7: 44572 | C7: 23.436602
A8: CNQ | B8: 44573 | C8: 23.822645
A9: CNQ | B9: 44574 | C9: 24.285894
A10: CNQ | B10: 44575 | C10: 25.162214
A11: CNQ | B11: 44578 | C11: 25.532816
A12: CNQ | B12: 44579 | C12: 25.509651
A13: CNQ | B13: 44580 | C13: 25.579144
... A4013: IMO | B4013: 46022 | C4013: 116.80293

Sheet Prices_2026
A1: Company | B1: Date | C1: Close
A2: CNQ | B2: 46024 | C2: 45.79171
A3: CNQ | B3: 46027 | C3: 43.031769
A4: CNQ | B4: 46028 | C4: 42.370937
A5: CNQ | B5: 46029 | C5: 41.185329
A6: CNQ | B6: 46030 | C6: 42.47784
A7: CNQ | B7: 46031 | C7: 43.362186
A8: CNQ | B8: 46034 | C8: 43.546829
A9: CNQ | B9: 46035 | C9: 44.693569
A10: CNQ | B10: 46036 | C10: 46.67606
A11: CNQ | B11: 46037 | C11: 46.102692
A12: CNQ | B12: 46038 | C12: 46.442829
A13: CNQ | B13: 46041 | C13: 46.695496
... A709: IMO | B709: 46280 | C709: 188.11

Sheet Year_End_Prices
A1: Company | B1: Year | C1: Close
A2: CNQ | B2: 2022 | C2: 31.554224
A3: SU | B3: 2022 | C3: 36.822819
A4: IMO | B4: 2022 | C4: 60.035564
A5: CVE | B5: 2022 | C5: 23.656223
A6: SU | B6: 2023 | C6: 38.19487
A7: IMO | B7: 2023 | C7: 70.624214
A8: CVE | B8: 2023 | C8: 20.327997
A9: CNQ | B9: 2023 | C9: 38.200382
A10: SU | B10: 2024 | C10: 48.179405
A11: CVE | B11: 2024 | C11: 20.761627
A12: IMO | B12: 2024 | C12: 85.010132
A13: CNQ | B13: 2024 | C13: 40.914742
... A21: IMO | B21: 2026 | C21: 188.11

Sheet Oil_Price
A1: Date | B1: Close
A2: 44564 | B2: 76.080002
A3: 44565 | B3: 76.989998
A4: 44566 | B4: 77.849998
A5: 44567 | B5: 79.459999
A6: 44568 | B6: 78.900002
A7: 44571 | B7: 78.230003
A8: 44572 | B8: 81.220001
A9: 44573 | B9: 82.639999
A10: 44574 | B10: 82.120003
A11: 44575 | B11: 83.82
A12: 44579 | B12: 85.43
A13: 44580 | B13: 86.959999
... A1187: 46287 | B1187: 90.900002
